<DataPump>
  <sourceConnection>
  	<driverName>org.h2.Driver</driverName>
    <connectionURL>jdbc:h2:tcp://localhost/~/test</connectionURL>
    <userId>sa</userId>
    <password></password>    
  </sourceConnection>
  <destConnection>
 <driverName>org.h2.Driver</driverName>
    <connectionURL>jdbc:h2:tcp://localhost/~/test</connectionURL>
    <userId>sa</userId>
    <password></password>  
  </destConnection> 
 <table>
    <sourceTable>Employee</sourceTable>
    <sourceSchema>source_schema</sourceSchema>
    <destTable>Employee</destTable>
    <destSchema>target_schema</destSchema>
    <forceMatch>true</forceMatch>
    <clause></clause>
    <columns>          
      <Column>        
        <destColumn>Role</destColumn>
        <value>Analyst</value>
      </Column>      
    </columns>
  </table>
 </DataPump>
